H2DatabaseJiaocheng/README.md
H2DatabaseJiaocheng/__init__.py
H2DatabaseJiaocheng/__main__.py
H2DatabaseJiaocheng/file.epub
H2DatabaseJiaocheng/index.html
H2DatabaseJiaocheng/css/__init__.py
H2DatabaseJiaocheng/css/annotations.css
H2DatabaseJiaocheng/css/main.css
H2DatabaseJiaocheng/css/normalize.css
H2DatabaseJiaocheng/css/popup.css
H2DatabaseJiaocheng/font/__init__.py
H2DatabaseJiaocheng/font/fontello.eot
H2DatabaseJiaocheng/font/fontello.svg
H2DatabaseJiaocheng/font/fontello.ttf
H2DatabaseJiaocheng/font/fontello.woff
H2DatabaseJiaocheng/img/__init__.py
H2DatabaseJiaocheng/img/annotator-glyph-sprite.png
H2DatabaseJiaocheng/img/annotator-icon-sprite.png
H2DatabaseJiaocheng/img/apple-touch-icon.png
H2DatabaseJiaocheng/img/cancelfullscreen.png
H2DatabaseJiaocheng/img/close.png
H2DatabaseJiaocheng/img/fullscreen.png
H2DatabaseJiaocheng/img/loader.gif
H2DatabaseJiaocheng/img/menu-icon.png
H2DatabaseJiaocheng/img/save.png
H2DatabaseJiaocheng/img/saved.png
H2DatabaseJiaocheng/img/settings-s.png
H2DatabaseJiaocheng/img/settings.png
H2DatabaseJiaocheng/img/star.png
H2DatabaseJiaocheng/js/__init__.py
H2DatabaseJiaocheng/js/epub.js
H2DatabaseJiaocheng/js/epub.min.js
H2DatabaseJiaocheng/js/epub.min.map
H2DatabaseJiaocheng/js/hooks.min.js
H2DatabaseJiaocheng/js/hooks.min.map
H2DatabaseJiaocheng/js/reader.js
H2DatabaseJiaocheng/js/reader.js.map
H2DatabaseJiaocheng/js/reader.min.js
H2DatabaseJiaocheng/js/reader.min.map
H2DatabaseJiaocheng/js/hooks/__init__.py
H2DatabaseJiaocheng/js/hooks/extensions/__init__.py
H2DatabaseJiaocheng/js/hooks/extensions/highlight.js
H2DatabaseJiaocheng/js/libs/__init__.py
H2DatabaseJiaocheng/js/libs/jquery.min.js
H2DatabaseJiaocheng/js/libs/localforage.min.js
H2DatabaseJiaocheng/js/libs/screenfull.js
H2DatabaseJiaocheng/js/libs/screenfull.min.js
H2DatabaseJiaocheng/js/libs/zip.min.js
H2DatabaseJiaocheng/js/plugins/__init__.py
H2DatabaseJiaocheng/js/plugins/hypothesis.js
H2DatabaseJiaocheng/js/plugins/search.js
h2_database_jiaocheng-2024.3.1.0.dist-info/METADATA
h2_database_jiaocheng-2024.3.1.0.dist-info/WHEEL
h2_database_jiaocheng-2024.3.1.0.dist-info/entry_points.txt
h2_database_jiaocheng-2024.3.1.0.dist-info/top_level.txt
h2_database_jiaocheng-2024.3.1.0.dist-info/RECORD
